HiveClient/HiveClient.py
HiveClient/__init__.py
hiveclient-1.0.4.dist-info/METADATA
hiveclient-1.0.4.dist-info/WHEEL
hiveclient-1.0.4.dist-info/top_level.txt
hiveclient-1.0.4.dist-info/RECORD
