Metadata-Version: 2.4
Name: HiveClient
Version: 1.0.4
Summary: Hive数据库连接工具类，支持查询执行与数据处理
Home-page: https://github.com/yourusername/hiveclient
Author: DongYang
Author-email: 649898871@qq.com
Classifier: Programming Language :: Python :: 3
Classifier: Programming Language :: Python :: 3.7
Classifier: Programming Language :: Python :: 3.8
Classifier: Programming Language :: Python :: 3.9
Classifier: Programming Language :: Python :: 3.10
Classifier: License :: OSI Approved :: MIT License
Classifier: Operating System :: OS Independent
Requires-Python: >=3.7
Requires-Dist: requests<2.32.0,>=2.25.0
Requires-Dist: thrift<0.20.0,>=0.15.0
Requires-Dist: thrift-sasl<0.5.0,>=0.4.3
Requires-Dist: pyhive<0.10.0,>=0.6.5
Requires-Dist: pandas<2.2.0,>=1.3.0
